{
  "customer": "DoorDash",
  "hierarchy": [
    {
      "position": 1,
      "newName": "Consumer Marketplace Platform",
      "components": [
        {
          "position": 1,
          "newName": "Discovery & Ordering Experience",
          "features": [
            { "position": 1, "newName": "Personalized Restaurant Recommendations" },
            { "position": 2, "newName": "Real-Time Order Tracking" },
            { "position": 3, "newName": "Group Ordering & Split Payments" },
            { "position": 4, "newName": "Reorder & Favorites" }
          ]
        },
        {
          "position": 2,
          "newName": "DashPass Subscription",
          "features": [
            { "position": 1, "newName": "Zero Delivery Fees" },
            { "position": 2, "newName": "Reduced Service Fees" },
            { "position": 3, "newName": "Member-Exclusive Offers" },
            { "position": 4, "newName": "Priority Support Access" }
          ]
        },
        {
          "position": 3,
          "newName": "Multi-Vertical Delivery",
          "features": [
            { "position": 1, "newName": "Grocery & Fresh Produce" },
            { "position": 2, "newName": "Alcohol & Beverage Delivery" },
            { "position": 3, "newName": "Convenience & Retail Items" },
            { "position": 4, "newName": "Package Pickup & Drop-off" }
          ]
        }
      ]
    },
    {
      "position": 2,
      "newName": "Merchant Commerce Platform",
      "components": [
        {
          "position": 1,
          "newName": "Storefront & Online Ordering",
          "features": [
            { "position": 1, "newName": "Branded Website Integration" },
            { "position": 2, "newName": "Commission-Free Direct Orders" },
            { "position": 3, "newName": "Menu Management Console" },
            { "position": 4, "newName": "Cross-Channel Loyalty Program" }
          ]
        },
        {
          "position": 2,
          "newName": "Operations & Order Management",
          "features": [
            { "position": 1, "newName": "Live Order Dashboard" },
            { "position": 2, "newName": "Customer Chat Communication" },
            { "position": 3, "newName": "Prep Time Optimization" },
            { "position": 4, "newName": "POS Integration Hub" }
          ]
        },
        {
          "position": 3,
          "newName": "Analytics & Business Insights",
          "features": [
            { "position": 1, "newName": "Sales Performance Dashboard" },
            { "position": 2, "newName": "Customer Demographics & Zip Codes" },
            { "position": 3, "newName": "Review Management & Response" },
            { "position": 4, "newName": "Financial Reporting & Payouts" }
          ]
        }
      ]
    }
  ]
}
